cli/__init__.py
cli/main.py
lex/__init__.py
lex/bots/PollexyHygieneBot.py
lex/bots/PollexySecondaryBot.py
lex/bots/PollexySetAlarmBot.py
lex/bots/__init__.py
lex/fluent/__init__.py
lex/fluent/bot.py
lex/fluent/intent.py
lex/fluent/message.py
lex/fluent/slot.py
luthor_for_lex-0.0.6.dist-info/DESCRIPTION.rst
luthor_for_lex-0.0.6.dist-info/METADATA
luthor_for_lex-0.0.6.dist-info/RECORD
luthor_for_lex-0.0.6.dist-info/WHEEL
luthor_for_lex-0.0.6.dist-info/entry_points.txt
luthor_for_lex-0.0.6.dist-info/metadata.json
luthor_for_lex-0.0.6.dist-info/top_level.txt
speaker/__init__.py
speaker/speaker.py
