Metadata-Version: 2.0
Name: luthor-for-lex
Version: 0.0.6
Summary: Easy Lex bot manager
Home-page: https://github.com/troylar/luthor-for-lex
Author: Troy Larson
Author-email: troylar@gmail.com
License: UNKNOWN
Platform: UNKNOWN
Classifier: Programming Language :: Python :: 3
Classifier: License :: OSI Approved :: MIT License
Classifier: Operating System :: OS Independent
